tdd_chatbot/__init__.py
tdd_chatbot/app.py
test/__init__.py
test/test_language.py
test/test_llm.py
test/test_voice.py
tdd_chatbot-0.1.0.dist-info/LICENSE
tdd_chatbot-0.1.0.dist-info/METADATA
tdd_chatbot-0.1.0.dist-info/WHEEL
tdd_chatbot-0.1.0.dist-info/top_level.txt
tdd_chatbot-0.1.0.dist-info/RECORD
