Metadata-Version: 2.1
Name: tdd-chatbot
Version: 0.1.0
Summary: Voice-based chatbot using Ollama LLM with TDD
Author: Kavisha Nilmani
Author-email: kavishanilmani@outlook.com
License: MIT
Classifier: Programming Language :: Python :: 3
Classifier: License :: OSI Approved :: MIT License
Classifier: Operating System :: OS Independent
Requires-Python: ==3.11.0
License-File: LICENSE
Requires-Dist: streamlit
Requires-Dist: speechrecognition
Requires-Dist: pyttsx3
Requires-Dist: requests
Requires-Dist: langdetect
